AUTHORS
LICENSE
MANIFEST.in
setup.cfg
setup.py
Fungiform.egg-info/PKG-INFO
Fungiform.egg-info/SOURCES.txt
Fungiform.egg-info/dependency_links.txt
Fungiform.egg-info/not-zip-safe
Fungiform.egg-info/top_level.txt
docs/.gitignore
docs/Makefile
docs/conf.py
docs/forms.rst
docs/index.rst
docs/license.rst
docs/make.bat
docs/widgets.rst
fungiform/__init__.py
fungiform/csrf.py
fungiform/exceptions.py
fungiform/forms.py
fungiform/recaptcha.py
fungiform/redirects.py
fungiform/utils.py
fungiform/widgets.py
fungiform/tests/__init__.py
fungiform/tests/forms.py
fungiform/tests/utils.py
fungiform/tests/widgets.py