Metadata-Version: 1.0
Name: Fungiform
Version: 0.1
Summary: form library
Home-page: http://github.com/mitsuhiko/fungiform
Author: Armin Ronacher
Author-email: armin.ronacher@active-4.com
License: BSD License
Keywords: form library
Platform: any
Classifier: Environment :: Web Environment
Classifier: Intended Audience :: Developers
Classifier: License :: OSI Approved :: BSD License
Classifier: Operating System :: OS Independent
Classifier: Programming Language :: Python
Classifier: Topic :: Internet :: WWW/HTTP :: Dynamic Content
Classifier: Topic :: Software Development :: Libraries :: Python Modules
Classifier: Development Status :: 4 - Beta
